{
  "activity_url": "http://concordfake.org/activities/123",
  "students": [
    {
      "name": "Kareem Nima",
      "username": "kareemnima90",
      "endpoint_url": "http://lara.blah/blah/sfdklsfklj_KEY"
    },
    {
      "name": "Min Tam",
      "username": "mintam942",
      "endpoint_url": "q5oh63aj91748bg"
    },
    {
      "name": "Shena Laura",
      "username": "shenalaura251",
      "endpoint_url": "mfto6lupa28bhnd"
    },
    {
      "name": "Matt Tam",
      "username": "matttam393",
      "endpoint_url": "cakg6w7hsmn9tul"
    },
    {
      "name": "Luna Nima",
      "username": "lunanima962",
      "endpoint_url": "42rmkw3exn5g9id"
    },
    {
      "name": "Matt Tam",
      "username": "matttam191",
      "endpoint_url": "924qawkog5ecfds"
    },
    {
      "name": "Shen Jim",
      "username": "shenjim694",
      "endpoint_url": "wgfscd5uqkn16ab"
    },
    {
      "name": "Nima Mirka",
      "username": "nimamirka24",
      "endpoint_url": "untgm5wr6i9hlbj"
    },
    {
      "name": "Jim Mirka",
      "username": "jimmirka134",
      "endpoint_url": "re83xs2nbw7ktld"
    },
    {
      "name": "Barny Max",
      "username": "barnymax578",
      "endpoint_url": "2q8c9x1n3gad6kt"
    },
    {
      "name": "Luna Nima",
      "username": "lunanima153",
      "endpoint_url": "ua5nb4o9hps86me"
    },
    {
      "name": "Luna Nima",
      "username": "lunanima579",
      "endpoint_url": "fdtiq23x4167ncs"
    }
  ]
}